{
	"name": "dynamic pipeline",
	"properties": {
		"activities": [
			{
				"name": "Get Metadata",
				"type": "GetMetadata",
				"dependsOn": [
					{
						"activity": "ForEach1",
						"dependencyConditions": [
							"Succeeded"
						]
					}
				],
				"policy": {
					"timeout": "0.12:00:00",
					"retry": 0,
					"retryIntervalInSeconds": 30,
					"secureOutput": false,
					"secureInput": false
				},
				"userProperties": [],
				"typeProperties": {
					"dataset": {
						"referenceName": "metadata",
						"type": "DatasetReference"
					},
					"fieldList": [
						"childItems"
					],
					"storeSettings": {
						"type": "AzureBlobFSReadSettings",
						"recursive": true,
						"enablePartitionDiscovery": false
					},
					"formatSettings": {
						"type": "DelimitedTextReadSettings"
					}
				}
			},
			{
				"name": "ForEach1",
				"type": "ForEach",
				"dependsOn": [
					{
						"activity": "Lookup",
						"dependencyConditions": [
							"Succeeded"
						]
					}
				],
				"userProperties": [],
				"typeProperties": {
					"items": {
						"value": "@activity('Lookup').output.value",
						"type": "Expression"
					},
					"isSequential": true,
					"activities": [
						{
							"name": "Copy data2",
							"type": "Copy",
							"dependsOn": [],
							"policy": {
								"timeout": "0.12:00:00",
								"retry": 0,
								"retryIntervalInSeconds": 30,
								"secureOutput": false,
								"secureInput": false
							},
							"userProperties": [],
							"typeProperties": {
								"source": {
									"type": "DelimitedTextSource",
									"storeSettings": {
										"type": "HttpReadSettings",
										"requestMethod": "GET"
									},
									"formatSettings": {
										"type": "DelimitedTextReadSettings"
									}
								},
								"sink": {
									"type": "DelimitedTextSink",
									"storeSettings": {
										"type": "AzureBlobFSWriteSettings"
									},
									"formatSettings": {
										"type": "DelimitedTextWriteSettings",
										"quoteAllText": true,
										"fileExtension": ".txt"
									}
								},
								"enableStaging": false,
								"translator": {
									"type": "TabularTranslator",
									"typeConversion": true,
									"typeConversionSettings": {
										"allowDataTruncation": true,
										"treatBooleanAsNumber": false
									}
								}
							},
							"inputs": [
								{
									"referenceName": "pkdata",
									"type": "DatasetReference",
									"parameters": {
										"csv_relative_url": {
											"value": "@item().csv_relative_url",
											"type": "Expression"
										}
									}
								}
							],
							"outputs": [
								{
									"referenceName": "sinkdata",
									"type": "DatasetReference",
									"parameters": {
										"file_name": {
											"value": "@item().file_name",
											"type": "Expression"
										}
									}
								}
							]
						}
					]
				}
			},
			{
				"name": "Lookup",
				"type": "Lookup",
				"dependsOn": [],
				"policy": {
					"timeout": "0.12:00:00",
					"retry": 0,
					"retryIntervalInSeconds": 30,
					"secureOutput": false,
					"secureInput": false
				},
				"userProperties": [],
				"typeProperties": {
					"source": {
						"type": "JsonSource",
						"storeSettings": {
							"type": "HttpReadSettings",
							"requestMethod": "GET"
						},
						"formatSettings": {
							"type": "JsonReadSettings"
						}
					},
					"dataset": {
						"referenceName": "Json_parameter",
						"type": "DatasetReference"
					},
					"firstRowOnly": false
				}
			},
			{
				"name": "ForEachmeta",
				"type": "ForEach",
				"dependsOn": [
					{
						"activity": "Get Metadata",
						"dependencyConditions": [
							"Succeeded"
						]
					}
				],
				"userProperties": [],
				"typeProperties": {
					"items": {
						"value": "@activity('Get Metadata').output.childItems",
						"type": "Expression"
					},
					"isSequential": true,
					"activities": [
						{
							"name": "if file matches",
							"type": "IfCondition",
							"dependsOn": [],
							"userProperties": [],
							"typeProperties": {
								"expression": {
									"value": "@startswith(item().name,'e')",
									"type": "Expression"
								},
								"ifTrueActivities": [
									{
										"name": "Copy e data",
										"type": "Copy",
										"dependsOn": [],
										"policy": {
											"timeout": "0.12:00:00",
											"retry": 0,
											"retryIntervalInSeconds": 30,
											"secureOutput": false,
											"secureInput": false
										},
										"userProperties": [],
										"typeProperties": {
											"source": {
												"type": "DelimitedTextSource",
												"storeSettings": {
													"type": "AzureBlobFSReadSettings",
													"recursive": true,
													"enablePartitionDiscovery": false
												},
												"formatSettings": {
													"type": "DelimitedTextReadSettings"
												}
											},
											"sink": {
												"type": "DelimitedTextSink",
												"storeSettings": {
													"type": "AzureBlobFSWriteSettings"
												},
												"formatSettings": {
													"type": "DelimitedTextWriteSettings",
													"quoteAllText": true,
													"fileExtension": ".txt"
												}
											},
											"enableStaging": false,
											"translator": {
												"type": "TabularTranslator",
												"typeConversion": true,
												"typeConversionSettings": {
													"allowDataTruncation": true,
													"treatBooleanAsNumber": false
												}
											}
										},
										"inputs": [
											{
												"referenceName": "after_if_data",
												"type": "DatasetReference",
												"parameters": {
													"filename": {
														"value": "@item().name",
														"type": "Expression"
													}
												}
											}
										],
										"outputs": [
											{
												"referenceName": "sinkifdata",
												"type": "DatasetReference",
												"parameters": {
													"filename": {
														"value": "@item().name",
														"type": "Expression"
													}
												}
											}
										]
									}
								]
							}
						}
					]
				}
			},
			{
				"name": "Data flow1",
				"type": "ExecuteDataFlow",
				"dependsOn": [
					{
						"activity": "ForEachmeta",
						"dependencyConditions": [
							"Succeeded"
						]
					}
				],
				"policy": {
					"timeout": "0.12:00:00",
					"retry": 0,
					"retryIntervalInSeconds": 30,
					"secureOutput": false,
					"secureInput": false
				},
				"userProperties": [],
				"typeProperties": {
					"dataflow": {
						"referenceName": "dataflow1",
						"type": "DataFlowReference"
					},
					"compute": {
						"coreCount": 8,
						"computeType": "General"
					},
					"traceLevel": "Fine"
				}
			}
		],
		"annotations": [],
		"lastPublishTime": "2026-02-24T07:05:32Z"
	},
	"type": "Microsoft.DataFactory/factories/pipelines"
}